{"chunk_definitions":[{"row":7,"row_count":1,"visible":true,"expansion_state":0,"options":{"engine":"r","label":"unnamed-chunk-19"},"document_id":"C0DF7C9D","chunk_id":"crg0ouikui1nv","chunk_label":"unnamed-chunk-1"},{"row":17,"row_count":1,"visible":true,"expansion_state":0,"options":{"engine":"r","label":"unnamed-chunk-2"},"document_id":"C0DF7C9D","chunk_id":"cpvciil71919r","chunk_label":"unnamed-chunk-2"},{"row":28,"row_count":1,"visible":true,"expansion_state":0,"options":{"engine":"r","label":"unnamed-chunk-21"},"document_id":"C0DF7C9D","chunk_id":"c3nnsz2hg8ois","chunk_label":"unnamed-chunk-3"},{"row":39,"row_count":1,"visible":true,"expansion_state":0,"options":{"engine":"r","label":"unnamed-chunk-27"},"document_id":"C0DF7C9D","chunk_id":"csuwuks399e7e","chunk_label":"unnamed-chunk-4"},{"row":51,"row_count":1,"visible":true,"expansion_state":0,"options":{"engine":"r","label":"unnamed-chunk-33"},"document_id":"C0DF7C9D","chunk_id":"cw4zkri2seab2","chunk_label":"unnamed-chunk-5"},{"row":95,"row_count":1,"visible":true,"expansion_state":0,"options":{"engine":"r","label":"unnamed-chunk-6"},"document_id":"C0DF7C9D","chunk_id":"cj0lbanljf834","chunk_label":"unnamed-chunk-6"}],"doc_write_time":1656578979}